[
    {
        "type": "p",
        "thickness": 6,
        "extra": "24_teeth_shield",
        "shaft": "motor_n20",
        "diameter": 1,
        "pos": [
            0,
            0,
            -4.25
        ],
        "shape": "pulley_gt2",
        "number_of_teeth": 24,
        "depth": 8.5
    },
    {
        "type": "p",
        "thickness": 6,
        "extra": "24_teeth_shield",
        "shaft": "motor_n20",
        "diameter": 1,
        "pos": [
            0,
            0,
            -3.75
        ],
        "shape": "oobb_cylinder",
        "radius": 8.643312101910828,
        "depth": 1
    },
    {
        "type": "p",
        "thickness": 6,
        "extra": "24_teeth_shield",
        "shaft": "motor_n20",
        "diameter": 1,
        "pos": [
            0,
            0,
            3.75
        ],
        "shape": "oobb_cylinder",
        "radius": 8.643312101910828,
        "depth": 1
    },
    {
        "type": "n",
        "thickness": 6,
        "extra": "24_teeth_shield",
        "shaft": "motor_n20",
        "diameter": 1,
        "pos": [
            0,
            0,
            0
        ],
        "shape": "oobb_holes",
        "width": 1,
        "height": 1,
        "both_holes": true,
        "circle": true,
        "middle": false
    },
    {
        "type": "n",
        "thickness": 6,
        "shaft": "motor_n20",
        "diameter": 1,
        "pos": [
            0,
            0,
            0
        ],
        "shape": "oobb_motor_n20",
        "part": "shaft",
        "m": "#"
    },
    {
        "type": "n",
        "thickness": 6,
        "extra": "24_teeth_shield",
        "shaft": "motor_n20",
        "diameter": 1,
        "pos": [
            0,
            0,
            0
        ],
        "shape": "oobb_slice"
    }
]